sideqr/__init__.py
sideqr/qr_scanner.py
sideqr-0.0.post20.dist-info/METADATA
sideqr-0.0.post20.dist-info/WHEEL
sideqr-0.0.post20.dist-info/top_level.txt
sideqr-0.0.post20.dist-info/RECORD
