Metadata-Version: 2.2
Name: sideqr
Version: 0.0.post20
Summary: A PySide6 library providing a custom QML component for QR code scanning.
Home-page: https://github.com/vishnumg/SideQR
Author: Vishnu Mohan G
Classifier: Programming Language :: Python :: 3
Classifier: License :: OSI Approved :: MIT License
Classifier: Operating System :: OS Independent
Requires-Dist: PySide6>=6.0.0
Requires-Dist: pyzbar
Requires-Dist: numpy
Requires-Dist: opencv-python
Dynamic: author
Dynamic: classifier
Dynamic: description
Dynamic: description-content-type
Dynamic: home-page
Dynamic: requires-dist
Dynamic: summary
